phise/__init__.py
phise/classes/__init__.py
phise/classes/camera.py
phise/classes/companion.py
phise/classes/context.py
phise/classes/interferometer.py
phise/classes/kernel_nuller.py
phise/classes/mmi.py
phise/classes/target.py
phise/classes/telescope.py
phise/modules/__init__.py
phise/modules/coordinates.py
phise/modules/ml.py
phise/modules/mmi.py
phise/modules/phase.py
phise/modules/signals.py
phise/modules/test_statistics.py
phise-0.1.1.dist-info/METADATA
phise-0.1.1.dist-info/WHEEL
phise-0.1.1.dist-info/top_level.txt
phise-0.1.1.dist-info/RECORD
