Metadata-Version: 2.4
Name: phise
Version: 0.1.1
Summary: Package for tunable kernel nulling / interferometry utilities (phise)
Author-email: Vincent Foriel <vincent.foriel@gmail.com>, VForiel <vince.lrf@gmail.com>, VForiel <vincent.foriel@gmail.com>
License: MIT
Requires-Python: >=3.11.0
Requires-Dist: numpy>=1.26.4
Requires-Dist: matplotlib>=3.10.3
Requires-Dist: astropy>=7.1.0
Requires-Dist: scipy>=1.16.0
Requires-Dist: ipywidgets>=8.1.7
Requires-Dist: sympy>=1.14.0
Requires-Dist: fitter>=1.7.1
Requires-Dist: numba>=0.61.2
Requires-Dist: LRFutils>=0.1.2
Requires-Dist: nbformat>=5.10.4
Requires-Dist: pip>=25.1.1
Requires-Dist: gitpython>=3.1.44
